main.py
setup.py
dbt_bytedhouse.egg-info/PKG-INFO
dbt_bytedhouse.egg-info/SOURCES.txt
dbt_bytedhouse.egg-info/dependency_links.txt
dbt_bytedhouse.egg-info/requires.txt
dbt_bytedhouse.egg-info/top_level.txt